JianmingPythonJiaocheng40/README.md
JianmingPythonJiaocheng40/__init__.py
JianmingPythonJiaocheng40/__main__.py
JianmingPythonJiaocheng40/file.epub
JianmingPythonJiaocheng40/index.html
JianmingPythonJiaocheng40/css/__init__.py
JianmingPythonJiaocheng40/css/annotations.css
JianmingPythonJiaocheng40/css/main.css
JianmingPythonJiaocheng40/css/normalize.css
JianmingPythonJiaocheng40/css/popup.css
JianmingPythonJiaocheng40/font/__init__.py
JianmingPythonJiaocheng40/font/fontello.eot
JianmingPythonJiaocheng40/font/fontello.svg
JianmingPythonJiaocheng40/font/fontello.ttf
JianmingPythonJiaocheng40/font/fontello.woff
JianmingPythonJiaocheng40/img/__init__.py
JianmingPythonJiaocheng40/img/annotator-glyph-sprite.png
JianmingPythonJiaocheng40/img/annotator-icon-sprite.png
JianmingPythonJiaocheng40/img/apple-touch-icon.png
JianmingPythonJiaocheng40/img/cancelfullscreen.png
JianmingPythonJiaocheng40/img/close.png
JianmingPythonJiaocheng40/img/fullscreen.png
JianmingPythonJiaocheng40/img/loader.gif
JianmingPythonJiaocheng40/img/menu-icon.png
JianmingPythonJiaocheng40/img/save.png
JianmingPythonJiaocheng40/img/saved.png
JianmingPythonJiaocheng40/img/settings-s.png
JianmingPythonJiaocheng40/img/settings.png
JianmingPythonJiaocheng40/img/star.png
JianmingPythonJiaocheng40/js/__init__.py
JianmingPythonJiaocheng40/js/epub.js
JianmingPythonJiaocheng40/js/epub.min.js
JianmingPythonJiaocheng40/js/epub.min.map
JianmingPythonJiaocheng40/js/hooks.min.js
JianmingPythonJiaocheng40/js/hooks.min.map
JianmingPythonJiaocheng40/js/reader.js
JianmingPythonJiaocheng40/js/reader.js.map
JianmingPythonJiaocheng40/js/reader.min.js
JianmingPythonJiaocheng40/js/reader.min.map
JianmingPythonJiaocheng40/js/hooks/__init__.py
JianmingPythonJiaocheng40/js/hooks/extensions/__init__.py
JianmingPythonJiaocheng40/js/hooks/extensions/highlight.js
JianmingPythonJiaocheng40/js/libs/__init__.py
JianmingPythonJiaocheng40/js/libs/jquery.min.js
JianmingPythonJiaocheng40/js/libs/localforage.min.js
jianming_python_jiaocheng_4_0-2024.3.3.0.dist-info/METADATA
jianming_python_jiaocheng_4_0-2024.3.3.0.dist-info/WHEEL
jianming_python_jiaocheng_4_0-2024.3.3.0.dist-info/entry_points.txt
jianming_python_jiaocheng_4_0-2024.3.3.0.dist-info/top_level.txt
jianming_python_jiaocheng_4_0-2024.3.3.0.dist-info/RECORD
